ask_mydb-0.1.0.dist-info/licenses/LICENSE
askmydb/__init__.py
askmydb/askmydb.py
ask_mydb-0.1.0.dist-info/METADATA
ask_mydb-0.1.0.dist-info/WHEEL
ask_mydb-0.1.0.dist-info/top_level.txt
ask_mydb-0.1.0.dist-info/RECORD
