Metadata-Version: 2.4
Name: ask-mydb
Version: 0.1.0
Summary: A Python package for querying databases using natural language.
Author: Shanthosh
License-Expression: MIT
License-File: LICENSE
Requires-Dist: sqlalchemy
Provides-Extra: dev
Requires-Dist: black; extra == "dev"
Requires-Dist: pytest; extra == "dev"
Provides-Extra: openai
Requires-Dist: openai; extra == "openai"
Provides-Extra: ollama
Requires-Dist: ollama; extra == "ollama"
Provides-Extra: all
Requires-Dist: sqlalchemy; extra == "all"
Requires-Dist: black; extra == "all"
Requires-Dist: pytest; extra == "all"
Requires-Dist: openai; extra == "all"
Requires-Dist: ollama; extra == "all"
Dynamic: author
Dynamic: license-file
